{
  "fio version" : "fio-3.36",
  "timestamp" : 1733177962,
  "timestamp_ms" : 1733177962669,
  "time" : "Mon Dec  2 22:19:22 2024",
  "jobs" : [
    {
      "jobname" : "rand_read_direct0_fsync0",
      "groupid" : 0,
      "job_start" : 1733177928560,
      "error" : 0,
      "eta" : 0,
      "elapsed" : 95,
      "job options" : {
        "name" : "rand_read_direct0_fsync0",
        "rw" : "randread",
        "direct" : "0",
        "bs" : "4k",
        "runtime" : "30",
        "ramp_time" : "60",
        "filename" : "/dev/mapper/secure",
        "iodepth" : "1",
        "numjobs" : "8"
      },
      "read" : {
        "io_bytes" : 3950182400,
        "io_kbytes" : 3857600,
        "bw_bytes" : 131668357,
        "bw" : 128582,
        "iops" : 32145.595147,
        "runtime" : 30001,
        "total_ios" : 964400,
        "short_ios" : 0,
        "drop_ios" : 0,
        "slat_ns" : {
          "min" : 0,
          "max" : 0,
          "mean" : 0.000000,
          "stddev" : 0.000000,
          "N" : 0
        },
        "clat_ns" : {
          "min" : 1500,
          "max" : 127760481,
          "mean" : 247466.435615,
          "stddev" : 722810.901858,
          "N" : 964400,
          "percentile" : {
            "1.000000" : 2800,
            "5.000000" : 166912,
            "10.000000" : 175104,
            "20.000000" : 185344,
            "30.000000" : 193536,
            "40.000000" : 201728,
            "50.000000" : 207872,
            "60.000000" : 216064,
            "70.000000" : 226304,
            "80.000000" : 240640,
            "90.000000" : 268288,
            "95.000000" : 313344,
            "99.000000" : 815104,
            "99.500000" : 1679360,
            "99.900000" : 5144576,
            "99.950000" : 9895936,
            "99.990000" : 30801920
          }
        },
        "lat_ns" : {
          "min" : 1600,
          "max" : 127760581,
          "mean" : 247574.685658,
          "stddev" : 722811.833706,
          "N" : 964400
        },
        "bw_min" : 100632,
        "bw_max" : 146728,
        "bw_agg" : 99.971707,
        "bw_mean" : 128546.745763,
        "bw_dev" : 1322.629717,
        "bw_samples" : 472,
        "iops_min" : 25158,
        "iops_max" : 36682,
        "iops_mean" : 32136.508475,
        "iops_stddev" : 330.651226,
        "iops_samples" : 472
      },
      "write" : {
        "io_bytes" : 0,
        "io_kbytes" : 0,
        "bw_bytes" : 0,
        "bw" : 0,
        "iops" : 0.000000,
        "runtime" : 0,
        "total_ios" : 0,
        "short_ios" : 0,
        "drop_ios" : 0,
        "slat_ns" : {
          "min" : 0,
          "max" : 0,
          "mean" : 0.000000,
          "stddev" : 0.000000,
          "N" : 0
        },
        "clat_ns" : {
          "min" : 0,
          "max" : 0,
          "mean" : 0.000000,
          "stddev" : 0.000000,
          "N" : 0
        },
        "lat_ns" : {
          "min" : 0,
          "max" : 0,
          "mean" : 0.000000,
          "stddev" : 0.000000,
          "N" : 0
        },
        "bw_min" : 0,
        "bw_max" : 0,
        "bw_agg" : 0.000000,
        "bw_mean" : 0.000000,
        "bw_dev" : 0.000000,
        "bw_samples" : 0,
        "iops_min" : 0,
        "iops_max" : 0,
        "iops_mean" : 0.000000,
        "iops_stddev" : 0.000000,
        "iops_samples" : 0
      },
      "trim" : {
        "io_bytes" : 0,
        "io_kbytes" : 0,
        "bw_bytes" : 0,
        "bw" : 0,
        "iops" : 0.000000,
        "runtime" : 0,
        "total_ios" : 0,
        "short_ios" : 0,
        "drop_ios" : 0,
        "slat_ns" : {
          "min" : 0,
          "max" : 0,
          "mean" : 0.000000,
          "stddev" : 0.000000,
          "N" : 0
        },
        "clat_ns" : {
          "min" : 0,
          "max" : 0,
          "mean" : 0.000000,
          "stddev" : 0.000000,
          "N" : 0
        },
        "lat_ns" : {
          "min" : 0,
          "max" : 0,
          "mean" : 0.000000,
          "stddev" : 0.000000,
          "N" : 0
        },
        "bw_min" : 0,
        "bw_max" : 0,
        "bw_agg" : 0.000000,
        "bw_mean" : 0.000000,
        "bw_dev" : 0.000000,
        "bw_samples" : 0,
        "iops_min" : 0,
        "iops_max" : 0,
        "iops_mean" : 0.000000,
        "iops_stddev" : 0.000000,
        "iops_samples" : 0
      },
      "sync" : {
        "total_ios" : 0,
        "lat_ns" : {
          "min" : 0,
          "max" : 0,
          "mean" : 0.000000,
          "stddev" : 0.000000,
          "N" : 0
        }
      },
      "job_runtime" : 240000,
      "usr_cpu" : 1.088750,
      "sys_cpu" : 8.142917,
      "ctx" : 1306474,
      "majf" : 0,
      "minf" : 293,
      "iodepth_level" : {
        "1" : 100.000000,
        "2" : 0.000000,
        "4" : 0.000000,
        "8" : 0.000000,
        "16" : 0.000000,
        "32" : 0.000000,
        ">=64" : 0.000000
      },
      "iodepth_submit" : {
        "0" : 0.000000,
        "4" : 100.000000,
        "8" : 0.000000,
        "16" : 0.000000,
        "32" : 0.000000,
        "64" : 0.000000,
        ">=64" : 0.000000
      },
      "iodepth_complete" : {
        "0" : 0.000000,
        "4" : 100.000000,
        "8" : 0.000000,
        "16" : 0.000000,
        "32" : 0.000000,
        "64" : 0.000000,
        ">=64" : 0.000000
      },
      "latency_ns" : {
        "2" : 0.000000,
        "4" : 0.000000,
        "10" : 0.000000,
        "20" : 0.000000,
        "50" : 0.000000,
        "100" : 0.000000,
        "250" : 0.000000,
        "500" : 0.000000,
        "750" : 0.000000,
        "1000" : 0.000000
      },
      "latency_us" : {
        "2" : 0.010000,
        "4" : 1.275612,
        "10" : 0.054438,
        "20" : 0.010000,
        "50" : 0.010000,
        "100" : 0.010000,
        "250" : 82.600788,
        "500" : 14.423891,
        "750" : 0.558378,
        "1000" : 0.204791
      },
      "latency_ms" : {
        "2" : 0.444007,
        "4" : 0.255288,
        "10" : 0.116549,
        "20" : 0.030796,
        "50" : 0.013998,
        "100" : 0.010000,
        "250" : 0.010000,
        "500" : 0.000000,
        "750" : 0.000000,
        "1000" : 0.000000,
        "2000" : 0.000000,
        ">=2000" : 0.000000
      },
      "latency_depth" : 1,
      "latency_target" : 0,
      "latency_percentile" : 100.000000,
      "latency_window" : 0
    }
  ]
}
