{
  "fio version" : "fio-3.36",
  "timestamp" : 1733281054,
  "timestamp_ms" : 1733281054480,
  "time" : "Wed Dec  4 02:57:34 2024",
  "jobs" : [
    {
      "jobname" : "write_direct0_fsync1_threads_4_3558",
      "groupid" : 0,
      "job_start" : 1733280994315,
      "error" : 0,
      "eta" : 0,
      "elapsed" : 91,
      "job options" : {
        "name" : "write_direct0_fsync1_threads_4_3558",
        "rw" : "write",
        "direct" : "0",
        "filename" : "/dev/mapper/secure",
        "numjobs" : "4",
        "fsync" : "1",
        "bs" : "4k",
        "ramp_time" : "30",
        "runtime" : "60",
        "iodepth" : "1",
        "end_fsync" : "1"
      },
      "read" : {
        "io_bytes" : 0,
        "io_kbytes" : 0,
        "bw_bytes" : 0,
        "bw" : 0,
        "iops" : 0.000000,
        "runtime" : 0,
        "total_ios" : 0,
        "short_ios" : 0,
        "drop_ios" : 0,
        "slat_ns" : {
          "min" : 0,
          "max" : 0,
          "mean" : 0.000000,
          "stddev" : 0.000000,
          "N" : 0
        },
        "clat_ns" : {
          "min" : 0,
          "max" : 0,
          "mean" : 0.000000,
          "stddev" : 0.000000,
          "N" : 0
        },
        "lat_ns" : {
          "min" : 0,
          "max" : 0,
          "mean" : 0.000000,
          "stddev" : 0.000000,
          "N" : 0
        },
        "bw_min" : 0,
        "bw_max" : 0,
        "bw_agg" : 0.000000,
        "bw_mean" : 0.000000,
        "bw_dev" : 0.000000,
        "bw_samples" : 0,
        "iops_min" : 0,
        "iops_max" : 0,
        "iops_mean" : 0.000000,
        "iops_stddev" : 0.000000,
        "iops_samples" : 0
      },
      "write" : {
        "io_bytes" : 2557902848,
        "io_kbytes" : 2497952,
        "bw_bytes" : 42631003,
        "bw" : 41631,
        "iops" : 10407.959867,
        "runtime" : 60001,
        "total_ios" : 624488,
        "short_ios" : 0,
        "drop_ios" : 0,
        "slat_ns" : {
          "min" : 0,
          "max" : 0,
          "mean" : 0.000000,
          "stddev" : 0.000000,
          "N" : 0
        },
        "clat_ns" : {
          "min" : 1900,
          "max" : 174802,
          "mean" : 4520.952968,
          "stddev" : 5367.120945,
          "N" : 624488,
          "percentile" : {
            "1.000000" : 2416,
            "5.000000" : 2416,
            "10.000000" : 2512,
            "20.000000" : 2608,
            "30.000000" : 2704,
            "40.000000" : 2896,
            "50.000000" : 3312,
            "60.000000" : 4128,
            "70.000000" : 4320,
            "80.000000" : 4896,
            "90.000000" : 5984,
            "95.000000" : 7072,
            "99.000000" : 37120,
            "99.500000" : 41216,
            "99.900000" : 60672,
            "99.950000" : 67072,
            "99.990000" : 85504
          }
        },
        "lat_ns" : {
          "min" : 2000,
          "max" : 175002,
          "mean" : 4664.550176,
          "stddev" : 5403.894642,
          "N" : 624488
        },
        "bw_min" : 37520,
        "bw_max" : 43560,
        "bw_agg" : 100.000000,
        "bw_mean" : 41648.441667,
        "bw_dev" : 243.571169,
        "bw_samples" : 480,
        "iops_min" : 9378,
        "iops_max" : 10890,
        "iops_mean" : 10412.016667,
        "iops_stddev" : 60.888644,
        "iops_samples" : 480
      },
      "trim" : {
        "io_bytes" : 0,
        "io_kbytes" : 0,
        "bw_bytes" : 0,
        "bw" : 0,
        "iops" : 0.000000,
        "runtime" : 0,
        "total_ios" : 0,
        "short_ios" : 0,
        "drop_ios" : 0,
        "slat_ns" : {
          "min" : 0,
          "max" : 0,
          "mean" : 0.000000,
          "stddev" : 0.000000,
          "N" : 0
        },
        "clat_ns" : {
          "min" : 0,
          "max" : 0,
          "mean" : 0.000000,
          "stddev" : 0.000000,
          "N" : 0
        },
        "lat_ns" : {
          "min" : 0,
          "max" : 0,
          "mean" : 0.000000,
          "stddev" : 0.000000,
          "N" : 0
        },
        "bw_min" : 0,
        "bw_max" : 0,
        "bw_agg" : 0.000000,
        "bw_mean" : 0.000000,
        "bw_dev" : 0.000000,
        "bw_samples" : 0,
        "iops_min" : 0,
        "iops_max" : 0,
        "iops_mean" : 0.000000,
        "iops_stddev" : 0.000000,
        "iops_samples" : 0
      },
      "sync" : {
        "total_ios" : 624488,
        "lat_ns" : {
          "min" : 155702,
          "max" : 45509085,
          "mean" : 378337.496626,
          "stddev" : 170934.250845,
          "N" : 624488,
          "percentile" : {
            "1.000000" : 284672,
            "5.000000" : 317440,
            "10.000000" : 329728,
            "20.000000" : 337920,
            "30.000000" : 346112,
            "40.000000" : 354304,
            "50.000000" : 358400,
            "60.000000" : 366592,
            "70.000000" : 378880,
            "80.000000" : 391168,
            "90.000000" : 411648,
            "95.000000" : 444416,
            "99.000000" : 987136,
            "99.500000" : 1236992,
            "99.900000" : 1712128,
            "99.950000" : 2039808,
            "99.990000" : 3260416
          }
        }
      },
      "job_runtime" : 240000,
      "usr_cpu" : 1.310000,
      "sys_cpu" : 9.849167,
      "ctx" : 684289,
      "majf" : 0,
      "minf" : 146,
      "iodepth_level" : {
        "1" : 200.000000,
        "2" : 0.000000,
        "4" : 0.000000,
        "8" : 0.000000,
        "16" : 0.000000,
        "32" : 0.000000,
        ">=64" : 0.000000
      },
      "iodepth_submit" : {
        "0" : 0.000000,
        "4" : 100.000000,
        "8" : 0.000000,
        "16" : 0.000000,
        "32" : 0.000000,
        "64" : 0.000000,
        ">=64" : 0.000000
      },
      "iodepth_complete" : {
        "0" : 0.000000,
        "4" : 100.000000,
        "8" : 0.000000,
        "16" : 0.000000,
        "32" : 0.000000,
        "64" : 0.000000,
        ">=64" : 0.000000
      },
      "latency_ns" : {
        "2" : 0.000000,
        "4" : 0.000000,
        "10" : 0.000000,
        "20" : 0.000000,
        "50" : 0.000000,
        "100" : 0.000000,
        "250" : 0.000000,
        "500" : 0.000000,
        "750" : 0.000000,
        "1000" : 0.000000
      },
      "latency_us" : {
        "2" : 0.010000,
        "4" : 56.556571,
        "10" : 40.753385,
        "20" : 0.676394,
        "50" : 1.753116,
        "100" : 0.255409,
        "250" : 0.010000,
        "500" : 0.000000,
        "750" : 0.000000,
        "1000" : 0.000000
      },
      "latency_ms" : {
        "2" : 0.000000,
        "4" : 0.000000,
        "10" : 0.000000,
        "20" : 0.000000,
        "50" : 0.000000,
        "100" : 0.000000,
        "250" : 0.000000,
        "500" : 0.000000,
        "750" : 0.000000,
        "1000" : 0.000000,
        "2000" : 0.000000,
        ">=2000" : 0.000000
      },
      "latency_depth" : 1,
      "latency_target" : 0,
      "latency_percentile" : 100.000000,
      "latency_window" : 0
    }
  ]
}
