{
  "fio version" : "fio-3.36",
  "timestamp" : 1733169883,
  "timestamp_ms" : 1733169883088,
  "time" : "Mon Dec  2 20:04:43 2024",
  "jobs" : [
    {
      "jobname" : "rand_read_direct1_fsync0",
      "groupid" : 0,
      "job_start" : 1733169853071,
      "error" : 0,
      "eta" : 0,
      "elapsed" : 91,
      "job options" : {
        "name" : "rand_read_direct1_fsync0",
        "rw" : "randread",
        "direct" : "1",
        "bs" : "4k",
        "runtime" : "30",
        "ramp_time" : "60",
        "filename" : "/dev/sdb1",
        "iodepth" : "1",
        "numjobs" : "4"
      },
      "read" : {
        "io_bytes" : 4304146432,
        "io_kbytes" : 4203268,
        "bw_bytes" : 143466765,
        "bw" : 140104,
        "iops" : 35026.065798,
        "runtime" : 30001,
        "total_ios" : 1050817,
        "short_ios" : 0,
        "drop_ios" : 0,
        "slat_ns" : {
          "min" : 0,
          "max" : 0,
          "mean" : 0.000000,
          "stddev" : 0.000000,
          "N" : 0
        },
        "clat_ns" : {
          "min" : 26800,
          "max" : 142301429,
          "mean" : 113318.235440,
          "stddev" : 262278.422238,
          "N" : 1050817,
          "percentile" : {
            "1.000000" : 60160,
            "5.000000" : 69120,
            "10.000000" : 73216,
            "20.000000" : 80384,
            "30.000000" : 84480,
            "40.000000" : 88576,
            "50.000000" : 92672,
            "60.000000" : 97792,
            "70.000000" : 103936,
            "80.000000" : 114176,
            "90.000000" : 140288,
            "95.000000" : 189440,
            "99.000000" : 561152,
            "99.500000" : 806912,
            "99.900000" : 1368064,
            "99.950000" : 1662976,
            "99.990000" : 4112384
          }
        },
        "lat_ns" : {
          "min" : 26900,
          "max" : 142301529,
          "mean" : 113389.553543,
          "stddev" : 262279.076092,
          "N" : 1050817
        },
        "bw_min" : 102427,
        "bw_max" : 163785,
        "bw_agg" : 100.000000,
        "bw_mean" : 140198.233333,
        "bw_dev" : 2897.996127,
        "bw_samples" : 240,
        "iops_min" : 25605,
        "iops_max" : 40945,
        "iops_mean" : 35049.066667,
        "iops_stddev" : 724.528864,
        "iops_samples" : 240
      },
      "write" : {
        "io_bytes" : 0,
        "io_kbytes" : 0,
        "bw_bytes" : 0,
        "bw" : 0,
        "iops" : 0.000000,
        "runtime" : 0,
        "total_ios" : 0,
        "short_ios" : 0,
        "drop_ios" : 0,
        "slat_ns" : {
          "min" : 0,
          "max" : 0,
          "mean" : 0.000000,
          "stddev" : 0.000000,
          "N" : 0
        },
        "clat_ns" : {
          "min" : 0,
          "max" : 0,
          "mean" : 0.000000,
          "stddev" : 0.000000,
          "N" : 0
        },
        "lat_ns" : {
          "min" : 0,
          "max" : 0,
          "mean" : 0.000000,
          "stddev" : 0.000000,
          "N" : 0
        },
        "bw_min" : 0,
        "bw_max" : 0,
        "bw_agg" : 0.000000,
        "bw_mean" : 0.000000,
        "bw_dev" : 0.000000,
        "bw_samples" : 0,
        "iops_min" : 0,
        "iops_max" : 0,
        "iops_mean" : 0.000000,
        "iops_stddev" : 0.000000,
        "iops_samples" : 0
      },
      "trim" : {
        "io_bytes" : 0,
        "io_kbytes" : 0,
        "bw_bytes" : 0,
        "bw" : 0,
        "iops" : 0.000000,
        "runtime" : 0,
        "total_ios" : 0,
        "short_ios" : 0,
        "drop_ios" : 0,
        "slat_ns" : {
          "min" : 0,
          "max" : 0,
          "mean" : 0.000000,
          "stddev" : 0.000000,
          "N" : 0
        },
        "clat_ns" : {
          "min" : 0,
          "max" : 0,
          "mean" : 0.000000,
          "stddev" : 0.000000,
          "N" : 0
        },
        "lat_ns" : {
          "min" : 0,
          "max" : 0,
          "mean" : 0.000000,
          "stddev" : 0.000000,
          "N" : 0
        },
        "bw_min" : 0,
        "bw_max" : 0,
        "bw_agg" : 0.000000,
        "bw_mean" : 0.000000,
        "bw_dev" : 0.000000,
        "bw_samples" : 0,
        "iops_min" : 0,
        "iops_max" : 0,
        "iops_mean" : 0.000000,
        "iops_stddev" : 0.000000,
        "iops_samples" : 0
      },
      "sync" : {
        "total_ios" : 0,
        "lat_ns" : {
          "min" : 0,
          "max" : 0,
          "mean" : 0.000000,
          "stddev" : 0.000000,
          "N" : 0
        }
      },
      "job_runtime" : 120000,
      "usr_cpu" : 4.048333,
      "sys_cpu" : 18.443333,
      "ctx" : 1050762,
      "majf" : 0,
      "minf" : 146,
      "iodepth_level" : {
        "1" : 100.000000,
        "2" : 0.000000,
        "4" : 0.000000,
        "8" : 0.000000,
        "16" : 0.000000,
        "32" : 0.000000,
        ">=64" : 0.000000
      },
      "iodepth_submit" : {
        "0" : 0.000000,
        "4" : 100.000000,
        "8" : 0.000000,
        "16" : 0.000000,
        "32" : 0.000000,
        "64" : 0.000000,
        ">=64" : 0.000000
      },
      "iodepth_complete" : {
        "0" : 0.000000,
        "4" : 100.000000,
        "8" : 0.000000,
        "16" : 0.000000,
        "32" : 0.000000,
        "64" : 0.000000,
        ">=64" : 0.000000
      },
      "latency_ns" : {
        "2" : 0.000000,
        "4" : 0.000000,
        "10" : 0.000000,
        "20" : 0.000000,
        "50" : 0.000000,
        "100" : 0.000000,
        "250" : 0.000000,
        "500" : 0.000000,
        "750" : 0.000000,
        "1000" : 0.000000
      },
      "latency_us" : {
        "2" : 0.000000,
        "4" : 0.000000,
        "10" : 0.000000,
        "20" : 0.000000,
        "50" : 0.036353,
        "100" : 64.244202,
        "250" : 32.629088,
        "500" : 1.867404,
        "750" : 0.644641,
        "1000" : 0.294342
      },
      "latency_ms" : {
        "2" : 0.253898,
        "4" : 0.018938,
        "10" : 0.010000,
        "20" : 0.010000,
        "50" : 0.010000,
        "100" : 0.000000,
        "250" : 0.010000,
        "500" : 0.000000,
        "750" : 0.000000,
        "1000" : 0.000000,
        "2000" : 0.000000,
        ">=2000" : 0.000000
      },
      "latency_depth" : 1,
      "latency_target" : 0,
      "latency_percentile" : 100.000000,
      "latency_window" : 0
    }
  ],
  "disk_util" : [
    {
      "name" : "sdb",
      "read_ios" : 3240616,
      "write_ios" : 0,
      "read_sectors" : 25924928,
      "write_sectors" : 0,
      "read_merges" : 0,
      "write_merges" : 0,
      "read_ticks" : 276032,
      "write_ticks" : 0,
      "in_queue" : 276032,
      "util" : 74.313699
    }
  ]
}
